{
  "Device": "MDSE",
  "ProcotoclHeader": "MDSE",
  "DeviceType": "Modbus",
  "ProtocolType": "Monitoring",
  "PageNumberIndex": 6,
  "Pages": [
    {
      "PageName": "Page4",
      "PageNumber": 4,
      "Parameters": [
        {
          "Name": "Device ID",
          "Signed": false,
          "EnableDataType": false,
          "MinVal": -1,
          "MaxVal": -1,
          "Field": "Id",
          "Expression": "{0}",
          "Precision": 0,
          "DataType": "String",
          "Evaluate": false,
          "ParameterType": "Id",
          "ParameterIndexes": [ 4 ],
          "Factor": 1
        },
        {
          "Name": "Timestamp",
          "Signed": false,
          "EnableDataType": false,
          "MinVal": -1,
          "MaxVal": -1,
          "Field": "DateAndTime",
          "Expression": "{0} * 256 * 256 * 256 + {1} * 256 * 256 + {2} * 256 + {3}",
          "Precision": 5,
          "DataType": "Epoch",
          "Evaluate": true,
          "ParameterType": "Data",
          "ParameterIndexes": [ 0, 1, 2, 3 ],
          "Factor": 1
        },
        {
          "Name": "DeviceId",
          "Signed": false,
          "EnableDataType": false,
          "MinVal": -1,
          "MaxVal": -1,
          "Field": "Id",
          "Expression": "{0}",
          "Precision": 0,
          "DataType": "Integer",
          "Evaluate": false,
          "ParameterType": "Data",
          "ParameterIndexes": [ 4 ],
          "Factor": 1
        },
        {
          "Name": "PageNumber",
          "Signed": false,
          "EnableDataType": false,
          "MinVal": -1,
          "MaxVal": -1,
          "Field": "Id",
          "Expression": "{0}",
          "Precision": 0,
          "DataType": "Integer",
          "Evaluate": false,
          "ParameterType": "Data",
          "ParameterIndexes": [ 6 ],
          "Factor": 1
        },
        {
          "Name": "(DSE) Oil Pressure (kPa)",
          "Signed": false,
          "EnableDataType": true,
          "MinVal": 0,
          "MaxVal": 0,
          "Field": "F1",
          "Expression": "{0} * 256 + {1}",
          "Precision": 5,
          "DataType": "Double",
          "Evaluate": true,
          "ParameterType": "Data",
          "ParameterIndexes": [ 10, 11 ],
          "Factor": 1
        },
        {
          "Name": "(DSE) Coolant Temperature (°C)",
          "Signed": true,
          "EnableDataType": true,
          "MinVal": 0,
          "MaxVal": 0,
          "Field": "F2",
          "Expression": "{0} * 256 + {1}",
          "Precision": 5,
          "DataType": "Double",
          "Evaluate": true,
          "ParameterType": "Data",
          "ParameterIndexes": [ 12, 13 ],
          "Factor": 1
        },
        {
          "Name": "(DSE) Oil Temperature (°C)",
          "Signed": true,
          "EnableDataType": true,
          "MinVal": 0,
          "MaxVal": 0,
          "Field": "F3",
          "Expression": "{0} * 256 + {1}",
          "Precision": 5,
          "DataType": "Double",
          "Evaluate": true,
          "ParameterType": "Data",
          "ParameterIndexes": [ 14, 15 ],
          "Factor": 1
        },
        {
          "Name": "(DSE) Fuel Level (%)",
          "Signed": false,
          "EnableDataType": true,
          "MinVal": 0,
          "MaxVal": 0,
          "Field": "F4",
          "Expression": "{0} * 256 + {1}",
          "Precision": 5,
          "DataType": "Double",
          "Evaluate": true,
          "ParameterType": "Data",
          "ParameterIndexes": [ 16, 17 ],
          "Factor": 1
        },
        {
          "Name": "(DSE) Charge Alternator Voltage (Vac)",
          "Signed": false,
          "EnableDataType": true,
          "MinVal": 0,
          "MaxVal": 0,
          "Field": "F5",
          "Expression": "{0} * 256 + {1}",
          "Precision": 5,
          "DataType": "Double",
          "Evaluate": true,
          "ParameterType": "Data",
          "ParameterIndexes": [ 18, 19 ],
          "Factor": 0.1
        },
        {
          "Name": "(DSE) Battery Voltage (Vdc)",
          "Signed": false,
          "EnableDataType": true,
          "MinVal": 0,
          "MaxVal": 0,
          "Field": "F6",
          "Expression": "{0} * 256 + {1}",
          "Precision": 5,
          "DataType": "Double",
          "Evaluate": true,
          "ParameterType": "Data",
          "ParameterIndexes": [ 20, 21 ],
          "Factor": 0.1
        },
        {
          "Name": "(DSE) Engine Speed (RPM)",
          "Signed": false,
          "EnableDataType": true,
          "MinVal": 0,
          "MaxVal": 0,
          "Field": "F7",
          "Expression": "{0} * 256 + {1}",
          "Precision": 5,
          "DataType": "Double",
          "Evaluate": true,
          "ParameterType": "Data",
          "ParameterIndexes": [ 22, 23 ],
          "Factor": 1
        },
        {
          "Name": "(DSE) Generator Frequency (Hz)",
          "Signed": false,
          "EnableDataType": true,
          "MinVal": 0,
          "MaxVal": 0,
          "Field": "F8",
          "Expression": "{0} * 256 + {1}",
          "Precision": 5,
          "DataType": "Double",
          "Evaluate": true,
          "ParameterType": "Data",
          "ParameterIndexes": [ 24, 25 ],
          "Factor": 0.1
        },
        {
          "Name": "(DSE) Generator L2-N Voltage (Vac)",
          "Signed": false,
          "EnableDataType": true,
          "MinVal": 0,
          "MaxVal": 0,
          "Field": "F10",
          "Expression": "{0} * 256 * 256 * 256 + {1} * 256 * 256 + {2} * 256 + {3}",
          "Precision": 5,
          "DataType": "Double",
          "Evaluate": true,
          "ParameterType": "Data",
          "ParameterIndexes": [ 26, 27, 8, 29 ],
          "Factor": 0.1
        },
        {
          "Name": "(DSE) Generator L3-N Voltage (Vac)",
          "Signed": false,
          "EnableDataType": true,
          "MinVal": 0,
          "MaxVal": 0,
          "Field": "F11",
          "Expression": "{0} * 256 * 256 * 256 + {1} * 256 * 256 + {2} * 256 + {3}",
          "Precision": 5,
          "DataType": "Double",
          "Evaluate": true,
          "ParameterType": "Data",
          "ParameterIndexes": [ 30, 31, 32, 33 ],
          "Factor": 0.1
        },
        {
          "Name": "(DSE) Generator L1-L2 Voltage (Vac)",
          "Signed": false,
          "EnableDataType": true,
          "MinVal": 0,
          "MaxVal": 0,
          "Field": "F12",
          "Expression": "{0} * 256 * 256 * 256 + {1} * 256 * 256 + {2} * 256 + {3}",
          "Precision": 5,
          "DataType": "Double",
          "Evaluate": true,
          "ParameterType": "Data",
          "ParameterIndexes": [ 34, 35, 36, 37 ],
          "Factor": 0.1
        },
        {
          "Name": "(DSE) Generator L2-L3 Voltage (Vac)",
          "Signed": false,
          "EnableDataType": true,
          "MinVal": 0,
          "MaxVal": 0,
          "Field": "F13",
          "Expression": "{0} * 256 * 256 * 256 + {1} * 256 * 256 + {2} * 256 + {3}",
          "Precision": 5,
          "DataType": "Double",
          "Evaluate": true,
          "ParameterType": "Data",
          "ParameterIndexes": [ 38, 39, 40, 41 ],
          "Factor": 0.1
        },
        {
          "Name": "(DSE) Generator L3-L1 Voltage (Vac)",
          "Signed": false,
          "EnableDataType": true,
          "MinVal": 0,
          "MaxVal": 0,
          "Field": "F14",
          "Expression": "{0} * 256 * 256 * 256 + {1} * 256 * 256 + {2} * 256 + {3}",
          "Precision": 5,
          "DataType": "Double",
          "Evaluate": true,
          "ParameterType": "Data",
          "ParameterIndexes": [ 42, 43, 44, 45 ],
          "Factor": 0.1
        },
        {
          "Name": "(DSE) Generator L1 Current (Aac)",
          "Signed": false,
          "EnableDataType": true,
          "MinVal": 0,
          "MaxVal": 0,
          "Field": "F15",
          "Expression": "{0} * 256 * 256 * 256 + {1} * 256 * 256 + {2} * 256 + {3}",
          "Precision": 5,
          "DataType": "Double",
          "Evaluate": true,
          "ParameterType": "Data",
          "ParameterIndexes": [ 46, 47, 48, 49 ],
          "Factor": 0.1
        },
        {
          "Name": "(DSE) Generator L2 Current (Aac)",
          "Signed": false,
          "EnableDataType": true,
          "MinVal": 0,
          "MaxVal": 0,
          "Field": "F16",
          "Expression": "{0} * 256 * 256 * 256 + {1} * 256 * 256 + {2} * 256 + {3}",
          "Precision": 5,
          "DataType": "Double",
          "Evaluate": true,
          "ParameterType": "Data",
          "ParameterIndexes": [ 50, 51, 52, 53 ],
          "Factor": 0.1
        },
        {
          "Name": "(DSE) Generator L3 Current (Aac)",
          "Signed": false,
          "EnableDataType": true,
          "MinVal": 0,
          "MaxVal": 0,
          "Field": "F17",
          "Expression": "{0} * 256 * 256 * 256 + {1} * 256 * 256 + {2} * 256 + {3}",
          "Precision": 5,
          "DataType": "Double",
          "Evaluate": true,
          "ParameterType": "Data",
          "ParameterIndexes": [ 54, 55, 56, 57 ],
          "Factor": 0.1
        },
        {
          "Name": "(DSE) Generator Earth Current (Aac)",
          "Signed": false,
          "EnableDataType": true,
          "MinVal": 0,
          "MaxVal": 0,
          "Field": "F18",
          "Expression": "{0} * 256 * 256 * 256 + {1} * 256 * 256 + {2} * 256 + {3}",
          "Precision": 5,
          "DataType": "Double",
          "Evaluate": true,
          "ParameterType": "Data",
          "ParameterIndexes": [ 58, 59, 60, 61 ],
          "Factor": 0.1
        },
        {
          "Name": "(DSE) Generator L1 Power (kW)",
          "Signed": true,
          "EnableDataType": true,
          "MinVal": 0,
          "MaxVal": 0,
          "Field": "F19",
          "Expression": "{0} * 256 * 256 * 256 + {1} * 256 * 256 + {2} * 256 + {3}",
          "Precision": 5,
          "DataType": "Double",
          "Evaluate": true,
          "ParameterType": "Data",
          "ParameterIndexes": [ 62, 63, 64, 65 ],
          "Factor": 0.001
        },
        {
          "Name": "(DSE) Generator L2 Power (kW)",
          "Signed": true,
          "EnableDataType": true,
          "MinVal": 0,
          "MaxVal": 0,
          "Field": "F20",
          "Expression": "{0} * 256 * 256 * 256 + {1} * 256 * 256 + {2} * 256 + {3}",
          "Precision": 5,
          "DataType": "Double",
          "Evaluate": true,
          "ParameterType": "Data",
          "ParameterIndexes": [ 66, 67, 68, 69 ],
          "Factor": 0.001
        },
        {
          "Name": "(DSE) Generator L3 Power (kW)",
          "Signed": true,
          "EnableDataType": true,
          "MinVal": 0,
          "MaxVal": 0,
          "Field": "F21",
          "Expression": "{0} * 256 * 256 * 256 + {1} * 256 * 256 + {2} * 256 + {3}",
          "Precision": 5,
          "DataType": "Double",
          "Evaluate": true,
          "ParameterType": "Data",
          "ParameterIndexes": [ 70, 71, 72, 73 ],
          "Factor": 0.001
        },
        {
          "Name": "(DSE) Generator Current Lag/Lead (degree)",
          "Signed": true,
          "EnableDataType": true,
          "MinVal": 0,
          "MaxVal": 0,
          "Field": "F22",
          "Expression": "{0} * 256 + {1}",
          "Precision": 5,
          "DataType": "Double",
          "Evaluate": true,
          "ParameterType": "Data",
          "ParameterIndexes": [ 74, 75 ],
          "Factor": 0.1
        },
        {
          "Name": "(DSE) Mains Frequency (Hz)",
          "Signed": false,
          "EnableDataType": true,
          "MinVal": 0,
          "MaxVal": 0,
          "Field": "F23",
          "Expression": "{0} * 256 + {1}",
          "Precision": 5,
          "DataType": "Double",
          "Evaluate": true,
          "ParameterType": "Data",
          "ParameterIndexes": [ 76, 77 ],
          "Factor": 0.1
        },
        {
          "Name": "(DSE) Mains L1-N Voltage (Vac)",
          "Signed": false,
          "EnableDataType": true,
          "MinVal": 0,
          "MaxVal": 0,
          "Field": "F24",
          "Expression": "{0} * 256 * 256 * 256 + {1} * 256 * 256 + {2} * 256 + {3}",
          "Precision": 5,
          "DataType": "Double",
          "Evaluate": true,
          "ParameterType": "Data",
          "ParameterIndexes": [ 78, 79, 80, 81 ],
          "Factor": 0.1
        },
        {
          "Name": "(DSE) Mains L2-N Voltage (Vac)",
          "Signed": false,
          "EnableDataType": true,
          "MinVal": 0,
          "MaxVal": 0,
          "Field": "F25",
          "Expression": "{0} * 256 * 256 * 256 + {1} * 256 * 256 + {2} * 256 + {3}",
          "Precision": 5,
          "DataType": "Double",
          "Evaluate": true,
          "ParameterType": "Data",
          "ParameterIndexes": [ 82, 83, 84, 85 ],
          "Factor": 0.1
        },
        {
          "Name": "(DSE) Mains L3-N Voltage (Vac)",
          "Signed": false,
          "EnableDataType": true,
          "MinVal": 0,
          "MaxVal": 0,
          "Field": "F26",
          "Expression": "{0} * 256 * 256 * 256 + {1} * 256 * 256 + {2} * 256 + {3}",
          "Precision": 5,
          "DataType": "Double",
          "Evaluate": true,
          "ParameterType": "Data",
          "ParameterIndexes": [ 86, 87, 88, 89 ],
          "Factor": 0.1
        },
        {
          "Name": "(DSE) Mains L1-L2 Voltage (Vac)",
          "Signed": false,
          "EnableDataType": true,
          "MinVal": 0,
          "MaxVal": 0,
          "Field": "F27",
          "Expression": "{0} * 256 * 256 * 256 + {1} * 256 * 256 + {2} * 256 + {3}",
          "Precision": 5,
          "DataType": "Double",
          "Evaluate": true,
          "ParameterType": "Data",
          "ParameterIndexes": [ 90, 91, 92, 93 ],
          "Factor": 0.1
        },
        {
          "Name": "(DSE) Mains L2-L3 Voltage (Vac)",
          "Signed": false,
          "EnableDataType": true,
          "MinVal": 0,
          "MaxVal": 0,
          "Field": "F28",
          "Expression": "{0} * 256 * 256 * 256 + {1} * 256 * 256 + {2} * 256 + {3}",
          "Precision": 5,
          "DataType": "Double",
          "Evaluate": true,
          "ParameterType": "Data",
          "ParameterIndexes": [ 94, 95, 96, 97 ],
          "Factor": 0.1
        },
        {
          "Name": "(DSE) Mains L3-L1 Voltage (Vac)",
          "Signed": false,
          "EnableDataType": true,
          "MinVal": 0,
          "MaxVal": 0,
          "Field": "F29",
          "Expression": "{0} * 256 * 256 * 256 + {1} * 256 * 256 + {2} * 256 + {3}",
          "Precision": 5,
          "DataType": "Double",
          "Evaluate": true,
          "ParameterType": "Data",
          "ParameterIndexes": [ 98, 99, 100, 101 ],
          "Factor": 0.1
        },
        {
          "Name": "(DSE) Mains Voltage Phase Lag/Lead (degree)",
          "Signed": true,
          "EnableDataType": true,
          "MinVal": 0,
          "MaxVal": 0,
          "Field": "F30",
          "Expression": "{0} * 256 + {1}",
          "Precision": 5,
          "DataType": "Double",
          "Evaluate": true,
          "ParameterType": "Data",
          "ParameterIndexes": [ 102, 103 ],
          "Factor": 1
        },
        {
          "Name": "(DSE) Generator Phase Rotation",
          "Signed": false,
          "EnableDataType": true,
          "MinVal": 0,
          "MaxVal": 0,
          "Field": "F31",
          "Expression": "{0} * 256 + {1}",
          "Precision": 5,
          "DataType": "Double",
          "Evaluate": true,
          "ParameterType": "Data",
          "ParameterIndexes": [ 104, 105 ],
          "Factor": 1
        },
        {
          "Name": "(DSE) Mains Phase Rotation",
          "Signed": false,
          "EnableDataType": true,
          "MinVal": 0,
          "MaxVal": 0,
          "Field": "F32",
          "Expression": "{0} * 256 + {1}",
          "Precision": 5,
          "DataType": "Double",
          "Evaluate": true,
          "ParameterType": "Data",
          "ParameterIndexes": [ 106, 107 ],
          "Factor": 1
        },
        {
          "Name": "(DSE) Generator L1-N Voltage (Vac)",
          "Signed": false,
          "EnableDataType": true,
          "MinVal": 0,
          "MaxVal": 0,
          "Field": "F9",
          "Expression": "{0} * 256 * 256 * 256 + {1} * 256 * 256 + {2} * 256 + {3}",
          "Precision": 5,
          "DataType": "Double",
          "Evaluate": true,
          "ParameterType": "Data",
          "ParameterIndexes": [ 108, 109, 110, 111 ],
          "Factor": 0.1
        }
      ]
    },
    {
      "PageName": "Page5",
      "PageNumber": 5,
      "Parameters": [
        {
          "Name": "Device ID",
          "Signed": false,
          "EnableDataType": false,
          "MinVal": -1,
          "MaxVal": -1,
          "Field": "Id",
          "Expression": "{0}",
          "Precision": 0,
          "DataType": "String",
          "Evaluate": false,
          "ParameterType": "Id",
          "ParameterIndexes": [ 4 ],
          "Factor": 1
        },
        {
          "Name": "Timestamp",
          "Signed": false,
          "EnableDataType": false,
          "MinVal": -1,
          "MaxVal": -1,
          "Field": "DateAndTime",
          "Expression": "{0} * 256 * 256 * 256 + {1} * 256 * 256 + {2} * 256 + {3}",
          "Precision": 5,
          "DataType": "Epoch",
          "Evaluate": true,
          "ParameterType": "Data",
          "ParameterIndexes": [ 0, 1, 2, 3 ],
          "Factor": 1
        },
        {
          "Name": "DeviceId",
          "Signed": false,
          "EnableDataType": false,
          "MinVal": -1,
          "MaxVal": -1,
          "Field": "Id",
          "Expression": "{0}",
          "Precision": 0,
          "DataType": "Integer",
          "Evaluate": false,
          "ParameterType": "Data",
          "ParameterIndexes": [ 4 ],
          "Factor": 1
        },
        {
          "Name": "PageNumber",
          "Signed": false,
          "EnableDataType": false,
          "MinVal": -1,
          "MaxVal": -1,
          "Field": "Id",
          "Expression": "{0}",
          "Precision": 0,
          "DataType": "Integer",
          "Evaluate": false,
          "ParameterType": "Data",
          "ParameterIndexes": [ 6 ],
          "Factor": 1
        },
        {
          "Name": "(DSE) Coolant Pressure 1 (kPa)",
          "Signed": false,
          "EnableDataType": true,
          "MinVal": 0,
          "MaxVal": 0,
          "Field": "F1",
          "Expression": "{0} * 256 + {1}",
          "Precision": 5,
          "DataType": "Double",
          "Evaluate": true,
          "ParameterType": "Data",
          "ParameterIndexes": [ 10, 11 ],
          "Factor": 1
        },
        {
          "Name": "(DSE) Coolant Pressure 2 (kPa)",
          "Signed": false,
          "EnableDataType": true,
          "MinVal": 0,
          "MaxVal": 0,
          "Field": "F2",
          "Expression": "{0} * 256 + {1}",
          "Precision": 5,
          "DataType": "Double",
          "Evaluate": true,
          "ParameterType": "Data",
          "ParameterIndexes": [ 12, 13 ],
          "Factor": 1
        },
        {
          "Name": "(DSE) Fuel Pressure 1 (kPa)",
          "Signed": false,
          "EnableDataType": true,
          "MinVal": 0,
          "MaxVal": 0,
          "Field": "F3",
          "Expression": "{0} * 256 + {1}",
          "Precision": 5,
          "DataType": "Double",
          "Evaluate": true,
          "ParameterType": "Data",
          "ParameterIndexes": [ 14, 15 ],
          "Factor": 1
        },
        {
          "Name": "(DSE) Fuel Pressure 2 (kPa)",
          "Signed": false,
          "EnableDataType": true,
          "MinVal": 0,
          "MaxVal": 0,
          "Field": "F4",
          "Expression": "{0} * 256 + {1}",
          "Precision": 5,
          "DataType": "Double",
          "Evaluate": true,
          "ParameterType": "Data",
          "ParameterIndexes": [ 16, 17 ],
          "Factor": 1
        },
        {
          "Name": "(DSE) Turbo Pressure 1 (kPa)",
          "Signed": false,
          "EnableDataType": true,
          "MinVal": 0,
          "MaxVal": 0,
          "Field": "F5",
          "Expression": "{0} * 256 + {1}",
          "Precision": 5,
          "DataType": "Double",
          "Evaluate": true,
          "ParameterType": "Data",
          "ParameterIndexes": [ 18, 19 ],
          "Factor": 1
        },
        {
          "Name": "(DSE) Turbo Pressure 2 (kPa)",
          "Signed": false,
          "EnableDataType": true,
          "MinVal": 0,
          "MaxVal": 0,
          "Field": "F6",
          "Expression": "{0} * 256 + {1}",
          "Precision": 5,
          "DataType": "Double",
          "Evaluate": true,
          "ParameterType": "Data",
          "ParameterIndexes": [ 20, 21 ],
          "Factor": 1
        },
        {
          "Name": "(DSE) Inlet Manifold Temperature 1 (°C)",
          "Signed": true,
          "EnableDataType": true,
          "MinVal": 0,
          "MaxVal": 0,
          "Field": "F7",
          "Expression": "{0} * 256 + {1}",
          "Precision": 5,
          "DataType": "Double",
          "Evaluate": true,
          "ParameterType": "Data",
          "ParameterIndexes": [ 22, 23 ],
          "Factor": 1
        },
        {
          "Name": "(DSE) Inlet Manifold Temperature 2 (°C)",
          "Signed": true,
          "EnableDataType": true,
          "MinVal": 0,
          "MaxVal": 0,
          "Field": "F8",
          "Expression": "{0} * 256 + {1}",
          "Precision": 5,
          "DataType": "Double",
          "Evaluate": true,
          "ParameterType": "Data",
          "ParameterIndexes": [ 24, 25 ],
          "Factor": 1
        },
        {
          "Name": "(DSE) Exhaust Temperature 1 (°C)",
          "Signed": true,
          "EnableDataType": true,
          "MinVal": 0,
          "MaxVal": 0,
          "Field": "F9",
          "Expression": "{0} * 256 + {1}",
          "Precision": 5,
          "DataType": "Double",
          "Evaluate": true,
          "ParameterType": "Data",
          "ParameterIndexes": [ 26, 27 ],
          "Factor": 1
        },
        {
          "Name": "(DSE) Exhaust Temperature 2 (°C)",
          "Signed": true,
          "EnableDataType": true,
          "MinVal": 0,
          "MaxVal": 0,
          "Field": "F10",
          "Expression": "{0} * 256 + {1}",
          "Precision": 5,
          "DataType": "Double",
          "Evaluate": true,
          "ParameterType": "Data",
          "ParameterIndexes": [ 28, 29 ],
          "Factor": 1
        },
        {
          "Name": "(DSE) Fuel Consumption (Ltr/h)",
          "Signed": false,
          "EnableDataType": true,
          "MinVal": 0,
          "MaxVal": 0,
          "Field": "F11",
          "Expression": "{0} * 256 * 256 * 256 + {1} * 256 * 256 + {2} * 256 + {3}",
          "Precision": 5,
          "DataType": "Double",
          "Evaluate": true,
          "ParameterType": "Data",
          "ParameterIndexes": [ 30, 31 ],
          "Factor": 0.01
        },
        {
          "Name": "(DSE) Water in Fuel",
          "Signed": false,
          "EnableDataType": true,
          "MinVal": 0,
          "MaxVal": 0,
          "Field": "F12",
          "Expression": "{0} * 256 + {1}",
          "Precision": 5,
          "DataType": "Double",
          "Evaluate": true,
          "ParameterType": "Data",
          "ParameterIndexes": [ 32, 33 ],
          "Factor": 1
        },
        {
          "Name": "(DSE) CAN Bit Data",
          "Signed": false,
          "EnableDataType": true,
          "MinVal": 0,
          "MaxVal": 0,
          "Field": "F13",
          "Expression": "{0} * 256 + {1}",
          "Precision": 5,
          "DataType": "Double",
          "Evaluate": true,
          "ParameterType": "Data",
          "ParameterIndexes": [ 34, 35 ],
          "Factor": 1
        },
        {
          "Name": "(DSE) Atmospheric Pressure (kPa)",
          "Signed": false,
          "EnableDataType": true,
          "MinVal": 0,
          "MaxVal": 0,
          "Field": "F14",
          "Expression": "{0} * 256 + {1}",
          "Precision": 5,
          "DataType": "Double",
          "Evaluate": true,
          "ParameterType": "Data",
          "ParameterIndexes": [ 36, 37 ],
          "Factor": 1
        },
        {
          "Name": "(DSE) Fuel Temperature (°C)",
          "Signed": true,
          "EnableDataType": true,
          "MinVal": 0,
          "MaxVal": 0,
          "Field": "F15",
          "Expression": "{0} * 256 + {1}",
          "Precision": 5,
          "DataType": "Double",
          "Evaluate": true,
          "ParameterType": "Data",
          "ParameterIndexes": [ 38, 39 ],
          "Factor": 1
        },
        {
          "Name": "(DSE) Fuel Level (Ltr)",
          "Signed": false,
          "EnableDataType": true,
          "MinVal": 0,
          "MaxVal": 0,
          "Field": "F16",
          "Expression": "{0} * 256 * 256 * 256 + {1} * 256 * 256 + {2} * 256 + {3}",
          "Precision": 5,
          "DataType": "Double",
          "Evaluate": true,
          "ParameterType": "Data",
          "ParameterIndexes": [ 40, 41 ],
          "Factor": 1
        }
      ]
    },
    {
      "PageName": "Page6",
      "PageNumber": 6,
      "Parameters": [
        {
          "Name": "Device ID",
          "Signed": false,
          "EnableDataType": false,
          "MinVal": -1,
          "MaxVal": -1,
          "Field": "Id",
          "Expression": "{0}",
          "Precision": 0,
          "DataType": "String",
          "Evaluate": false,
          "ParameterType": "Id",
          "ParameterIndexes": [ 4 ],
          "Factor": 1
        },
        {
          "Name": "Timestamp",
          "Signed": false,
          "EnableDataType": false,
          "MinVal": -1,
          "MaxVal": -1,
          "Field": "DateAndTime",
          "Expression": "{0} * 256 * 256 * 256 + {1} * 256 * 256 + {2} * 256 + {3}",
          "Precision": 5,
          "DataType": "Epoch",
          "Evaluate": true,
          "ParameterType": "Data",
          "ParameterIndexes": [ 0, 1, 2, 3 ],
          "Factor": 1
        },
        {
          "Name": "DeviceId",
          "Signed": false,
          "EnableDataType": false,
          "MinVal": -1,
          "MaxVal": -1,
          "Field": "Id",
          "Expression": "{0}",
          "Precision": 0,
          "DataType": "Integer",
          "Evaluate": false,
          "ParameterType": "Data",
          "ParameterIndexes": [ 4 ],
          "Factor": 1
        },
        {
          "Name": "PageNumber",
          "Signed": false,
          "EnableDataType": false,
          "MinVal": -1,
          "MaxVal": -1,
          "Field": "Id",
          "Expression": "{0}",
          "Precision": 0,
          "DataType": "Integer",
          "Evaluate": false,
          "ParameterType": "Data",
          "ParameterIndexes": [ 6 ],
          "Factor": 1
        },
        {
          "Name": "(DSE) Generator Total Power (kW)",
          "Signed": true,
          "EnableDataType": true,
          "MinVal": 0,
          "MaxVal": 0,
          "Field": "F1",
          "Expression": "{0} * 256 * 256 * 256 + {1} * 256 * 256 + {2} * 256 + {3}",
          "Precision": 5,
          "DataType": "Double",
          "Evaluate": true,
          "ParameterType": "Data",
          "ParameterIndexes": [ 10, 11 ],
          "Factor": 0.001
        },
        {
          "Name": "(DSE) Generator L1 Apparent Power (kVA)",
          "Signed": false,
          "EnableDataType": true,
          "MinVal": 0,
          "MaxVal": 0,
          "Field": "F2",
          "Expression": "{0} * 256 * 256 * 256 + {1} * 256 * 256 + {2} * 256 + {3}",
          "Precision": 5,
          "DataType": "Double",
          "Evaluate": true,
          "ParameterType": "Data",
          "ParameterIndexes": [ 12, 13 ],
          "Factor": 0.001
        },
        {
          "Name": "(DSE) Generator L2 Apparent Power (kVA)",
          "Signed": false,
          "EnableDataType": true,
          "MinVal": 0,
          "MaxVal": 0,
          "Field": "F3",
          "Expression": "{0} * 256 * 256 * 256 + {1} * 256 * 256 + {2} * 256 + {3}",
          "Precision": 5,
          "DataType": "Double",
          "Evaluate": true,
          "ParameterType": "Data",
          "ParameterIndexes": [ 14, 15 ],
          "Factor": 0.001
        },
        {
          "Name": "(DSE) Generator L3 Apparent Power (kVA)",
          "Signed": false,
          "EnableDataType": true,
          "MinVal": 0,
          "MaxVal": 0,
          "Field": "F4",
          "Expression": "{0} * 256 * 256 * 256 + {1} * 256 * 256 + {2} * 256 + {3}",
          "Precision": 5,
          "DataType": "Double",
          "Evaluate": true,
          "ParameterType": "Data",
          "ParameterIndexes": [ 16, 17 ],
          "Factor": 0.001
        },
        {
          "Name": "(DSE) Generator Total Apparent Power (kVA)",
          "Signed": true,
          "EnableDataType": true,
          "MinVal": 0,
          "MaxVal": 0,
          "Field": "F5",
          "Expression": "{0} * 256 * 256 * 256 + {1} * 256 * 256 + {2} * 256 + {3}",
          "Precision": 5,
          "DataType": "Double",
          "Evaluate": true,
          "ParameterType": "Data",
          "ParameterIndexes": [ 18, 19 ],
          "Factor": 0.001
        },
        {
          "Name": "(DSE) Generator L1 Reactive Power (kvar)",
          "Signed": true,
          "EnableDataType": true,
          "MinVal": 0,
          "MaxVal": 0,
          "Field": "F6",
          "Expression": "{0} * 256 * 256 * 256 + {1} * 256 * 256 + {2} * 256 + {3}",
          "Precision": 5,
          "DataType": "Double",
          "Evaluate": true,
          "ParameterType": "Data",
          "ParameterIndexes": [ 20, 21 ],
          "Factor": 0.001
        },
        {
          "Name": "(DSE) Generator L2 Reactive Power (kvar)",
          "Signed": true,
          "EnableDataType": true,
          "MinVal": 0,
          "MaxVal": 0,
          "Field": "F7",
          "Expression": "{0} * 256 * 256 * 256 + {1} * 256 * 256 + {2} * 256 + {3}",
          "Precision": 5,
          "DataType": "Double",
          "Evaluate": true,
          "ParameterType": "Data",
          "ParameterIndexes": [ 22, 23 ],
          "Factor": 0.001
        },
        {
          "Name": "(DSE) Generator L3 Reactive Power (kvar)",
          "Signed": true,
          "EnableDataType": true,
          "MinVal": 0,
          "MaxVal": 0,
          "Field": "F8",
          "Expression": "{0} * 256 * 256 * 256 + {1} * 256 * 256 + {2} * 256 + {3}",
          "Precision": 5,
          "DataType": "Double",
          "Evaluate": true,
          "ParameterType": "Data",
          "ParameterIndexes": [ 24, 25 ],
          "Factor": 0.001
        },
        {
          "Name": "(DSE) Generator Total Reactive Power (kvar)",
          "Signed": true,
          "EnableDataType": true,
          "MinVal": 0,
          "MaxVal": 0,
          "Field": "F9",
          "Expression": "{0} * 256 * 256 * 256 + {1} * 256 * 256 + {2} * 256 + {3}",
          "Precision": 5,
          "DataType": "Double",
          "Evaluate": true,
          "ParameterType": "Data",
          "ParameterIndexes": [ 26, 27 ],
          "Factor": 0.001
        },
        {
          "Name": "(DSE) Generator Power Factor L1",
          "Signed": true,
          "EnableDataType": true,
          "MinVal": 0,
          "MaxVal": 0,
          "Field": "F10",
          "Expression": "{0} * 256 + {1}",
          "Precision": 5,
          "DataType": "Double",
          "Evaluate": true,
          "ParameterType": "Data",
          "ParameterIndexes": [ 28, 29 ],
          "Factor": 0.01
        },
        {
          "Name": "(DSE) Generator Power Factor L2",
          "Signed": true,
          "EnableDataType": true,
          "MinVal": 0,
          "MaxVal": 0,
          "Field": "F11",
          "Expression": "{0} * 256 + {1}",
          "Precision": 5,
          "DataType": "Double",
          "Evaluate": true,
          "ParameterType": "Data",
          "ParameterIndexes": [ 30, 31 ],
          "Factor": 0.01
        },
        {
          "Name": "(DSE) Generator Power Factor L3",
          "Signed": true,
          "EnableDataType": true,
          "MinVal": 0,
          "MaxVal": 0,
          "Field": "F12",
          "Expression": "{0} * 256 + {1}",
          "Precision": 5,
          "DataType": "Double",
          "Evaluate": true,
          "ParameterType": "Data",
          "ParameterIndexes": [ 32, 33 ],
          "Factor": 0.01
        },
        {
          "Name": "(DSE) Generator Average Power Factor",
          "Signed": true,
          "EnableDataType": true,
          "MinVal": 0,
          "MaxVal": 0,
          "Field": "F13",
          "Expression": "{0} * 256 + {1}",
          "Precision": 5,
          "DataType": "Double",
          "Evaluate": true,
          "ParameterType": "Data",
          "ParameterIndexes": [ 34, 35 ],
          "Factor": 0.01
        }
      ]
    },
    {
      "PageName": "Page7",
      "PageNumber": 7,
      "Parameters": [
        {
          "Name": "Device ID",
          "Signed": false,
          "EnableDataType": false,
          "MinVal": -1,
          "MaxVal": -1,
          "Field": "Id",
          "Expression": "{0}",
          "Precision": 0,
          "DataType": "String",
          "Evaluate": false,
          "ParameterType": "Id",
          "ParameterIndexes": [ 4 ],
          "Factor": 1
        },
        {
          "Name": "Timestamp",
          "Signed": false,
          "EnableDataType": false,
          "MinVal": -1,
          "MaxVal": -1,
          "Field": "DateAndTime",
          "Expression": "{0} * 256 * 256 * 256 + {1} * 256 * 256 + {2} * 256 + {3}",
          "Precision": 5,
          "DataType": "Epoch",
          "Evaluate": true,
          "ParameterType": "Data",
          "ParameterIndexes": [ 0, 1, 2, 3 ],
          "Factor": 1
        },
        {
          "Name": "DeviceId",
          "Signed": false,
          "EnableDataType": false,
          "MinVal": -1,
          "MaxVal": -1,
          "Field": "Id",
          "Expression": "{0}",
          "Precision": 0,
          "DataType": "Integer",
          "Evaluate": false,
          "ParameterType": "Data",
          "ParameterIndexes": [ 4 ],
          "Factor": 1
        },
        {
          "Name": "PageNumber",
          "Signed": false,
          "EnableDataType": false,
          "MinVal": -1,
          "MaxVal": -1,
          "Field": "Id",
          "Expression": "{0}",
          "Precision": 0,
          "DataType": "Integer",
          "Evaluate": false,
          "ParameterType": "Data",
          "ParameterIndexes": [ 6 ],
          "Factor": 1
        },
        {
          "Name": "(DSE) Engine Run Time (Hrs)",
          "Signed": false,
          "EnableDataType": true,
          "MinVal": 0,
          "MaxVal": 0,
          "Field": "F1",
          "Expression": "{0} * 256 * 256 * 256 + {1} * 256 * 256 + {2} * 256 + {3}",
          "Precision": 5,
          "DataType": "Double",
          "Evaluate": true,
          "ParameterType": "Data",
          "ParameterIndexes": [ 10, 11 ],
          "Factor": 0.000277778
        },
        {
          "Name": "(DSE) Generator Energy (kWh)",
          "Signed": false,
          "EnableDataType": true,
          "MinVal": 0,
          "MaxVal": 0,
          "Field": "F2",
          "Expression": "{0} * 256 * 256 * 256 + {1} * 256 * 256 + {2} * 256 + {3}",
          "Precision": 5,
          "DataType": "Double",
          "Evaluate": true,
          "ParameterType": "Data",
          "ParameterIndexes": [ 12, 13 ],
          "Factor": 0.1
        },
        {
          "Name": "(DSE) Generator Negative Energy (kWh)",
          "Signed": false,
          "EnableDataType": true,
          "MinVal": 0,
          "MaxVal": 0,
          "Field": "F3",
          "Expression": "{0} * 256 * 256 * 256 + {1} * 256 * 256 + {2} * 256 + {3}",
          "Precision": 5,
          "DataType": "Double",
          "Evaluate": true,
          "ParameterType": "Data",
          "ParameterIndexes": [ 14, 15 ],
          "Factor": 0.1
        },
        {
          "Name": "(DSE) Generator Apparent Energy (kVAh)",
          "Signed": false,
          "EnableDataType": true,
          "MinVal": 0,
          "MaxVal": 0,
          "Field": "F4",
          "Expression": "{0} * 256 * 256 * 256 + {1} * 256 * 256 + {2} * 256 + {3}",
          "Precision": 5,
          "DataType": "Double",
          "Evaluate": true,
          "ParameterType": "Data",
          "ParameterIndexes": [ 16, 17 ],
          "Factor": 0.1
        },
        {
          "Name": "(DSE) Generator Reactive Energy (kVArh)",
          "Signed": false,
          "EnableDataType": true,
          "MinVal": 0,
          "MaxVal": 0,
          "Field": "F5",
          "Expression": "{0} * 256 * 256 * 256 + {1} * 256 * 256 + {2} * 256 + {3}",
          "Precision": 5,
          "DataType": "Double",
          "Evaluate": true,
          "ParameterType": "Data",
          "ParameterIndexes": [ 18, 19 ],
          "Factor": 0.1
        },
        {
          "Name": "(DSE) Number Of Starts",
          "Signed": false,
          "EnableDataType": true,
          "MinVal": 0,
          "MaxVal": 0,
          "Field": "F6",
          "Expression": "{0} * 256 * 256 * 256 + {1} * 256 * 256 + {2} * 256 + {3}",
          "Precision": 5,
          "DataType": "Double",
          "Evaluate": true,
          "ParameterType": "Data",
          "ParameterIndexes": [ 20, 21 ],
          "Factor": 1
        },
        {
          "Name": "(DSE) Mains Energy (kWh)",
          "Signed": false,
          "EnableDataType": true,
          "MinVal": 0,
          "MaxVal": 0,
          "Field": "F7",
          "Expression": "{0} * 256 * 256 * 256 + {1} * 256 * 256 + {2} * 256 + {3}",
          "Precision": 5,
          "DataType": "Double",
          "Evaluate": true,
          "ParameterType": "Data",
          "ParameterIndexes": [ 22, 23 ],
          "Factor": 0.1
        }

      ]
    },
    {
      "PageName": "Page8",
      "PageNumber": 8,
      "Parameters": [
        {
          "Name": "Device ID",
          "Signed": false,
          "EnableDataType": false,
          "MinVal": -1,
          "MaxVal": -1,
          "Field": "Id",
          "Expression": "{0}",
          "Precision": 0,
          "DataType": "String",
          "Evaluate": false,
          "ParameterType": "Id",
          "ParameterIndexes": [ 4 ],
          "Factor": 1
        },
        {
          "Name": "Timestamp",
          "Signed": false,
          "EnableDataType": false,
          "MinVal": -1,
          "MaxVal": -1,
          "Field": "DateAndTime",
          "Expression": "{0} * 256 * 256 * 256 + {1} * 256 * 256 + {2} * 256 + {3}",
          "Precision": 5,
          "DataType": "Epoch",
          "Evaluate": true,
          "ParameterType": "Data",
          "ParameterIndexes": [ 0, 1, 2, 3 ],
          "Factor": 1
        },
        {
          "Name": "DeviceId",
          "Signed": false,
          "EnableDataType": false,
          "MinVal": -1,
          "MaxVal": -1,
          "Field": "Id",
          "Expression": "{0}",
          "Precision": 0,
          "DataType": "Integer",
          "Evaluate": false,
          "ParameterType": "Data",
          "ParameterIndexes": [ 4 ],
          "Factor": 1
        },
        {
          "Name": "PageNumber",
          "Signed": false,
          "EnableDataType": false,
          "MinVal": -1,
          "MaxVal": -1,
          "Field": "Id",
          "Expression": "{0}",
          "Precision": 0,
          "DataType": "Integer",
          "Evaluate": false,
          "ParameterType": "Data",
          "ParameterIndexes": [ 6 ],
          "Factor": 1
        },
        {
          "Name": "(DSE) Number Of Named Alarms",
          "Signed": false,
          "EnableDataType": true,
          "MinVal": 0,
          "MaxVal": 0,
          "Field": "F1",
          "Expression": "{0} * 256 + {1}",
          "Precision": 5,
          "DataType": "Double",
          "Evaluate": true,
          "ParameterType": "Data",
          "ParameterIndexes": [ 10, 11 ],
          "Factor": 1
        },
        {
          "Name": "(DSE) Emergency Stop",
          "Signed": false,
          "EnableDataType": true,
          "MinVal": 0,
          "MaxVal": 0,
          "Field": "F2",
          "Expression": "{0} / 16 + 240",
          "Precision": 5,
          "DataType": "Integer",
          "Evaluate": true,
          "ParameterType": "Data",
          "ParameterIndexes": [ 12 ],
          "Factor": 1
        },
        {
          "Name": "(DSE) Low Oil Pressure",
          "Signed": false,
          "EnableDataType": true,
          "MinVal": 0,
          "MaxVal": 0,
          "Field": "F3",
          "Expression": "{0} / 1 + 15",
          "Precision": 5,
          "DataType": "Integer",
          "Evaluate": true,
          "ParameterType": "Data",
          "ParameterIndexes": [ 12 ],
          "Factor": 1
        },
        {
          "Name": "(DSE) High Coolant Temperature",
          "Signed": false,
          "EnableDataType": true,
          "MinVal": 0,
          "MaxVal": 0,
          "Field": "F4",
          "Expression": "{0} / 16 + 240",
          "Precision": 5,
          "DataType": "Integer",
          "Evaluate": true,
          "ParameterType": "Data",
          "ParameterIndexes": [ 13 ],
          "Factor": 1
        },
        {
          "Name": "(DSE) High Oil Temperature",
          "Signed": false,
          "EnableDataType": true,
          "MinVal": 0,
          "MaxVal": 0,
          "Field": "F5",
          "Expression": "{0} / 1 + 15",
          "Precision": 5,
          "DataType": "Integer",
          "Evaluate": true,
          "ParameterType": "Data",
          "ParameterIndexes": [ 13 ],
          "Factor": 1
        },
        {
          "Name": "(DSE) Under Speed",
          "Signed": false,
          "EnableDataType": true,
          "MinVal": 0,
          "MaxVal": 0,
          "Field": "F6",
          "Expression": "{0} / 16 + 240",
          "Precision": 5,
          "DataType": "Integer",
          "Evaluate": true,
          "ParameterType": "Data",
          "ParameterIndexes": [ 14 ],
          "Factor": 1
        },
        {
          "Name": "(DSE) Over Speed",
          "Signed": false,
          "EnableDataType": true,
          "MinVal": 0,
          "MaxVal": 0,
          "Field": "F7",
          "Expression": "{0} / 1 + 15",
          "Precision": 5,
          "DataType": "Integer",
          "Evaluate": true,
          "ParameterType": "Data",
          "ParameterIndexes": [ 14 ],
          "Factor": 1
        },
        {
          "Name": "(DSE) Fail To Start",
          "Signed": false,
          "EnableDataType": true,
          "MinVal": 0,
          "MaxVal": 0,
          "Field": "F8",
          "Expression": "{0} / 16 + 240",
          "Precision": 5,
          "DataType": "Integer",
          "Evaluate": true,
          "ParameterType": "Data",
          "ParameterIndexes": [ 15 ],
          "Factor": 1
        },
        {
          "Name": "(DSE) Fail To Come To Rest",
          "Signed": false,
          "EnableDataType": true,
          "MinVal": 0,
          "MaxVal": 0,
          "Field": "F9",
          "Expression": "{0} / 1 + 15",
          "Precision": 5,
          "DataType": "Integer",
          "Evaluate": true,
          "ParameterType": "Data",
          "ParameterIndexes": [ 15 ],
          "Factor": 1
        },
        {
          "Name": "(DSE) Loss Of Speed Sensing",
          "Signed": false,
          "EnableDataType": true,
          "MinVal": 0,
          "MaxVal": 0,
          "Field": "F10",
          "Expression": "{0} / 16 + 240",
          "Precision": 5,
          "DataType": "Integer",
          "Evaluate": true,
          "ParameterType": "Data",
          "ParameterIndexes": [ 16 ],
          "Factor": 1
        },
        {
          "Name": "(DSE) Generator Low Voltage",
          "Signed": false,
          "EnableDataType": true,
          "MinVal": 0,
          "MaxVal": 0,
          "Field": "F11",
          "Expression": "{0} / 1 + 15",
          "Precision": 5,
          "DataType": "Integer",
          "Evaluate": true,
          "ParameterType": "Data",
          "ParameterIndexes": [ 16 ],
          "Factor": 1
        },
        {
          "Name": "(DSE) Generator High Voltage",
          "Signed": false,
          "EnableDataType": true,
          "MinVal": 0,
          "MaxVal": 0,
          "Field": "F12",
          "Expression": "{0} / 16 + 240",
          "Precision": 5,
          "DataType": "Integer",
          "Evaluate": true,
          "ParameterType": "Data",
          "ParameterIndexes": [ 17 ],
          "Factor": 1
        },
        {
          "Name": "(DSE) Generator Low Frequency",
          "Signed": false,
          "EnableDataType": true,
          "MinVal": 0,
          "MaxVal": 0,
          "Field": "F13",
          "Expression": "{0} / 1 + 15",
          "Precision": 5,
          "DataType": "Integer",
          "Evaluate": true,
          "ParameterType": "Data",
          "ParameterIndexes": [ 17 ],
          "Factor": 1
        },
        {
          "Name": "(DSE) Generator High Frequency",
          "Signed": false,
          "EnableDataType": true,
          "MinVal": 0,
          "MaxVal": 0,
          "Field": "F14",
          "Expression": "{0} / 16 + 240",
          "Precision": 5,
          "DataType": "Integer",
          "Evaluate": true,
          "ParameterType": "Data",
          "ParameterIndexes": [ 18 ],
          "Factor": 1
        },
        {
          "Name": "(DSE) Generator High Current",
          "Signed": false,
          "EnableDataType": true,
          "MinVal": 0,
          "MaxVal": 0,
          "Field": "F15",
          "Expression": "{0} / 1 + 15",
          "Precision": 5,
          "DataType": "Integer",
          "Evaluate": true,
          "ParameterType": "Data",
          "ParameterIndexes": [ 18 ],
          "Factor": 1
        },
        {
          "Name": "(DSE) Generator Earth Fault",
          "Signed": false,
          "EnableDataType": true,
          "MinVal": 0,
          "MaxVal": 0,
          "Field": "F16",
          "Expression": "{0} / 16 + 240",
          "Precision": 5,
          "DataType": "Integer",
          "Evaluate": true,
          "ParameterType": "Data",
          "ParameterIndexes": [ 19 ],
          "Factor": 1
        },
        {
          "Name": "(DSE) Generator Reverse Power",
          "Signed": false,
          "EnableDataType": true,
          "MinVal": 0,
          "MaxVal": 0,
          "Field": "F17",
          "Expression": "{0} / 1 + 15",
          "Precision": 5,
          "DataType": "Integer",
          "Evaluate": true,
          "ParameterType": "Data",
          "ParameterIndexes": [ 19 ],
          "Factor": 1
        },
        {
          "Name": "(DSE) Air Flap",
          "Signed": false,
          "EnableDataType": true,
          "MinVal": 0,
          "MaxVal": 0,
          "Field": "F18",
          "Expression": "{0} / 16 + 240",
          "Precision": 5,
          "DataType": "Integer",
          "Evaluate": true,
          "ParameterType": "Data",
          "ParameterIndexes": [ 20 ],
          "Factor": 1
        },
        {
          "Name": "(DSE) Oil Pressure Sender Fault",
          "Signed": false,
          "EnableDataType": true,
          "MinVal": 0,
          "MaxVal": 0,
          "Field": "F19",
          "Expression": "{0} / 1 + 15",
          "Precision": 5,
          "DataType": "Integer",
          "Evaluate": true,
          "ParameterType": "Data",
          "ParameterIndexes": [ 20 ],
          "Factor": 1
        },
        {
          "Name": "(DSE) Coolant Temperature Sender Fault",
          "Signed": false,
          "EnableDataType": true,
          "MinVal": 0,
          "MaxVal": 0,
          "Field": "F20",
          "Expression": "{0} / 16 + 240",
          "Precision": 5,
          "DataType": "Integer",
          "Evaluate": true,
          "ParameterType": "Data",
          "ParameterIndexes": [ 21 ],
          "Factor": 1
        },
        {
          "Name": "(DSE) Oil Temperature Sender Fault",
          "Signed": false,
          "EnableDataType": true,
          "MinVal": 0,
          "MaxVal": 0,
          "Field": "F21",
          "Expression": "{0} / 1 + 15",
          "Precision": 5,
          "DataType": "Integer",
          "Evaluate": true,
          "ParameterType": "Data",
          "ParameterIndexes": [ 21 ],
          "Factor": 1
        },
        {
          "Name": "(DSE) Fuel Level Sender Fault",
          "Signed": false,
          "EnableDataType": true,
          "MinVal": 0,
          "MaxVal": 0,
          "Field": "F22",
          "Expression": "{0} / 16 + 240",
          "Precision": 5,
          "DataType": "Integer",
          "Evaluate": true,
          "ParameterType": "Data",
          "ParameterIndexes": [ 22 ],
          "Factor": 1
        },
        {
          "Name": "(DSE) Magnetic Pickup Fault",
          "Signed": false,
          "EnableDataType": true,
          "MinVal": 0,
          "MaxVal": 0,
          "Field": "F23",
          "Expression": "{0} / 1 + 15",
          "Precision": 5,
          "DataType": "Integer",
          "Evaluate": true,
          "ParameterType": "Data",
          "ParameterIndexes": [ 22 ],
          "Factor": 1
        },
        {
          "Name": "(DSE) Loss Of Ac Speed Signal",
          "Signed": false,
          "EnableDataType": true,
          "MinVal": 0,
          "MaxVal": 0,
          "Field": "F24",
          "Expression": "{0} / 16 + 240",
          "Precision": 5,
          "DataType": "Integer",
          "Evaluate": true,
          "ParameterType": "Data",
          "ParameterIndexes": [ 23 ],
          "Factor": 1
        },
        {
          "Name": "(DSE) Charge Alternator Failure",
          "Signed": false,
          "EnableDataType": true,
          "MinVal": 0,
          "MaxVal": 0,
          "Field": "F25",
          "Expression": "{0} / 1 + 15",
          "Precision": 5,
          "DataType": "Integer",
          "Evaluate": true,
          "ParameterType": "Data",
          "ParameterIndexes": [ 23 ],
          "Factor": 1
        },
        {
          "Name": "(DSE) Low Battery Voltage",
          "Signed": false,
          "EnableDataType": true,
          "MinVal": 0,
          "MaxVal": 0,
          "Field": "F26",
          "Expression": "{0} / 16 + 240",
          "Precision": 5,
          "DataType": "Integer",
          "Evaluate": true,
          "ParameterType": "Data",
          "ParameterIndexes": [ 24 ],
          "Factor": 1
        },
        {
          "Name": "(DSE) High Battery Voltage",
          "Signed": false,
          "EnableDataType": true,
          "MinVal": 0,
          "MaxVal": 0,
          "Field": "F27",
          "Expression": "{0} / 1 + 15",
          "Precision": 5,
          "DataType": "Integer",
          "Evaluate": true,
          "ParameterType": "Data",
          "ParameterIndexes": [ 24 ],
          "Factor": 1
        },
        {
          "Name": "(DSE) Low Fuel Level",
          "Signed": false,
          "EnableDataType": true,
          "MinVal": 0,
          "MaxVal": 0,
          "Field": "F28",
          "Expression": "{0} / 16 + 240",
          "Precision": 5,
          "DataType": "Integer",
          "Evaluate": true,
          "ParameterType": "Data",
          "ParameterIndexes": [ 25 ],
          "Factor": 1
        },
        {
          "Name": "(DSE) High Fuel Level",
          "Signed": false,
          "EnableDataType": true,
          "MinVal": 0,
          "MaxVal": 0,
          "Field": "F29",
          "Expression": "{0} / 1 + 15",
          "Precision": 5,
          "DataType": "Integer",
          "Evaluate": true,
          "ParameterType": "Data",
          "ParameterIndexes": [ 25 ],
          "Factor": 1
        },
        {
          "Name": "(DSE) Generator Failed To Close",
          "Signed": false,
          "EnableDataType": true,
          "MinVal": 0,
          "MaxVal": 0,
          "Field": "F30",
          "Expression": "{0} / 16 + 240",
          "Precision": 5,
          "DataType": "Integer",
          "Evaluate": true,
          "ParameterType": "Data",
          "ParameterIndexes": [ 26 ],
          "Factor": 1
        },
        {
          "Name": "(DSE) Mains Failed To Close",
          "Signed": false,
          "EnableDataType": true,
          "MinVal": 0,
          "MaxVal": 0,
          "Field": "F31",
          "Expression": "{0} / 1 + 15",
          "Precision": 5,
          "DataType": "Integer",
          "Evaluate": true,
          "ParameterType": "Data",
          "ParameterIndexes": [ 26 ],
          "Factor": 1
        },
        {
          "Name": "(DSE) Generator Failed To Open",
          "Signed": false,
          "EnableDataType": true,
          "MinVal": 0,
          "MaxVal": 0,
          "Field": "F32",
          "Expression": "{0} / 16 + 240",
          "Precision": 5,
          "DataType": "Integer",
          "Evaluate": true,
          "ParameterType": "Data",
          "ParameterIndexes": [ 27 ],
          "Factor": 1
        },
        {
          "Name": "(DSE) Mains Failed To Open",
          "Signed": false,
          "EnableDataType": true,
          "MinVal": 0,
          "MaxVal": 0,
          "Field": "F33",
          "Expression": "{0} / 1 + 15",
          "Precision": 5,
          "DataType": "Integer",
          "Evaluate": true,
          "ParameterType": "Data",
          "ParameterIndexes": [ 27 ],
          "Factor": 1
        },
        {
          "Name": "(DSE) Mains Low Voltage",
          "Signed": false,
          "EnableDataType": true,
          "MinVal": 0,
          "MaxVal": 0,
          "Field": "F34",
          "Expression": "{0} / 16 + 240",
          "Precision": 5,
          "DataType": "Integer",
          "Evaluate": true,
          "ParameterType": "Data",
          "ParameterIndexes": [ 28 ],
          "Factor": 1
        },
        {
          "Name": "(DSE) Mains High Voltage",
          "Signed": false,
          "EnableDataType": true,
          "MinVal": 0,
          "MaxVal": 0,
          "Field": "F35",
          "Expression": "{0} / 1 + 15",
          "Precision": 5,
          "DataType": "Integer",
          "Evaluate": true,
          "ParameterType": "Data",
          "ParameterIndexes": [ 28 ],
          "Factor": 1
        },
        {
          "Name": "(DSE) Bus Failed To Close",
          "Signed": false,
          "EnableDataType": true,
          "MinVal": 0,
          "MaxVal": 0,
          "Field": "F36",
          "Expression": "{0} / 16 + 240",
          "Precision": 5,
          "DataType": "Integer",
          "Evaluate": true,
          "ParameterType": "Data",
          "ParameterIndexes": [ 29 ],
          "Factor": 1
        },
        {
          "Name": "(DSE) Bus Failed To Open",
          "Signed": false,
          "EnableDataType": true,
          "MinVal": 0,
          "MaxVal": 0,
          "Field": "F37",
          "Expression": "{0} / 1 + 15",
          "Precision": 5,
          "DataType": "Integer",
          "Evaluate": true,
          "ParameterType": "Data",
          "ParameterIndexes": [ 29 ],
          "Factor": 1
        },
        {
          "Name": "(DSE) Mains Low Frequency",
          "Signed": false,
          "EnableDataType": true,
          "MinVal": 0,
          "MaxVal": 0,
          "Field": "F38",
          "Expression": "{0} / 16 + 240",
          "Precision": 5,
          "DataType": "Integer",
          "Evaluate": true,
          "ParameterType": "Data",
          "ParameterIndexes": [ 30 ],
          "Factor": 1
        },
        {
          "Name": "(DSE) Mains High Frequency",
          "Signed": false,
          "EnableDataType": true,
          "MinVal": 0,
          "MaxVal": 0,
          "Field": "F39",
          "Expression": "{0} / 1 + 15",
          "Precision": 5,
          "DataType": "Integer",
          "Evaluate": true,
          "ParameterType": "Data",
          "ParameterIndexes": [ 30 ],
          "Factor": 1
        },
        {
          "Name": "(DSE) Mains Failed",
          "Signed": false,
          "EnableDataType": true,
          "MinVal": 0,
          "MaxVal": 0,
          "Field": "F40",
          "Expression": "{0} / 16 + 240",
          "Precision": 5,
          "DataType": "Integer",
          "Evaluate": true,
          "ParameterType": "Data",
          "ParameterIndexes": [ 31 ],
          "Factor": 1
        },
        {
          "Name": "(DSE) Mains Phase Rotation Wrong",
          "Signed": false,
          "EnableDataType": true,
          "MinVal": 0,
          "MaxVal": 0,
          "Field": "F41",
          "Expression": "{0} / 1 + 15",
          "Precision": 5,
          "DataType": "Integer",
          "Evaluate": true,
          "ParameterType": "Data",
          "ParameterIndexes": [ 31 ],
          "Factor": 1
        },
        {
          "Name": "(DSE) Generator Phase Rotation Wrong",
          "Signed": false,
          "EnableDataType": true,
          "MinVal": 0,
          "MaxVal": 0,
          "Field": "F42",
          "Expression": "{0} / 16 + 240",
          "Precision": 5,
          "DataType": "Integer",
          "Evaluate": true,
          "ParameterType": "Data",
          "ParameterIndexes": [ 32 ],
          "Factor": 1
        },
        {
          "Name": "(DSE) Maintenance Due",
          "Signed": false,
          "EnableDataType": true,
          "MinVal": 0,
          "MaxVal": 0,
          "Field": "F43",
          "Expression": "{0} / 1 + 15",
          "Precision": 5,
          "DataType": "Integer",
          "Evaluate": true,
          "ParameterType": "Data",
          "ParameterIndexes": [ 32 ],
          "Factor": 1
        },
        {
          "Name": "(DSE) Clock Not Set",
          "Signed": false,
          "EnableDataType": true,
          "MinVal": 0,
          "MaxVal": 0,
          "Field": "F44",
          "Expression": "{0} / 16 + 240",
          "Precision": 5,
          "DataType": "Integer",
          "Evaluate": true,
          "ParameterType": "Data",
          "ParameterIndexes": [ 33 ],
          "Factor": 1
        },
        {
          "Name": "(DSE) Local Lcd Configuration Lost",
          "Signed": false,
          "EnableDataType": true,
          "MinVal": 0,
          "MaxVal": 0,
          "Field": "F45",
          "Expression": "{0} / 1 + 15",
          "Precision": 5,
          "DataType": "Integer",
          "Evaluate": true,
          "ParameterType": "Data",
          "ParameterIndexes": [ 33 ],
          "Factor": 1
        },
        {
          "Name": "(DSE) Local Telemetry Configuration Lost",
          "Signed": false,
          "EnableDataType": true,
          "MinVal": 0,
          "MaxVal": 0,
          "Field": "F46",
          "Expression": "{0} / 16 + 240",
          "Precision": 5,
          "DataType": "Integer",
          "Evaluate": true,
          "ParameterType": "Data",
          "ParameterIndexes": [ 34 ],
          "Factor": 1
        },
        {
          "Name": "(DSE) Control Unit Not Calibrated",
          "Signed": false,
          "EnableDataType": true,
          "MinVal": 0,
          "MaxVal": 0,
          "Field": "F47",
          "Expression": "{0} / 1 + 15",
          "Precision": 5,
          "DataType": "Integer",
          "Evaluate": true,
          "ParameterType": "Data",
          "ParameterIndexes": [ 34 ],
          "Factor": 1
        },
        {
          "Name": "(DSE) Modem Power Fault",
          "Signed": false,
          "EnableDataType": true,
          "MinVal": 0,
          "MaxVal": 0,
          "Field": "F48",
          "Expression": "{0} / 16 + 240",
          "Precision": 5,
          "DataType": "Integer",
          "Evaluate": true,
          "ParameterType": "Data",
          "ParameterIndexes": [ 35 ],
          "Factor": 1
        },
        {
          "Name": "(DSE) Generator Short Circuit",
          "Signed": false,
          "EnableDataType": true,
          "MinVal": 0,
          "MaxVal": 0,
          "Field": "F49",
          "Expression": "{0} / 1 + 15",
          "Precision": 5,
          "DataType": "Integer",
          "Evaluate": true,
          "ParameterType": "Data",
          "ParameterIndexes": [ 35 ],
          "Factor": 1
        }

      ]
    },
    {
      "PageName": "Page12",
      "PageNumber": 12,
      "Parameters": [
        {
          "Name": "Device ID",
          "Signed": false,
          "EnableDataType": false,
          "MinVal": -1,
          "MaxVal": -1,
          "Field": "Id",
          "Expression": "{0}",
          "Precision": 0,
          "DataType": "String",
          "Evaluate": false,
          "ParameterType": "Id",
          "ParameterIndexes": [ 4 ],
          "Factor": 1
        },
        {
          "Name": "Timestamp",
          "Signed": false,
          "EnableDataType": false,
          "MinVal": -1,
          "MaxVal": -1,
          "Field": "DateAndTime",
          "Expression": "{0} * 256 * 256 * 256 + {1} * 256 * 256 + {2} * 256 + {3}",
          "Precision": 5,
          "DataType": "Epoch",
          "Evaluate": true,
          "ParameterType": "Data",
          "ParameterIndexes": [ 0, 1, 2, 3 ],
          "Factor": 1
        },
        {
          "Name": "DeviceId",
          "Signed": false,
          "EnableDataType": false,
          "MinVal": -1,
          "MaxVal": -1,
          "Field": "Id",
          "Expression": "{0}",
          "Precision": 0,
          "DataType": "Integer",
          "Evaluate": false,
          "ParameterType": "Data",
          "ParameterIndexes": [ 4 ],
          "Factor": 1
        },
        {
          "Name": "PageNumber",
          "Signed": false,
          "EnableDataType": false,
          "MinVal": -1,
          "MaxVal": -1,
          "Field": "Id",
          "Expression": "{0}",
          "Precision": 0,
          "DataType": "Integer",
          "Evaluate": false,
          "ParameterType": "Data",
          "ParameterIndexes": [ 6 ],
          "Factor": 1
        },
        {
          "Name": "(DSE) Number of Digital Inputs",
          "Signed": false,
          "EnableDataType": true,
          "MinVal": 0,
          "MaxVal": 0,
          "Field": "F1",
          "Expression": "{0} * 256 + {1}",
          "Precision": 5,
          "DataType": "Double",
          "Evaluate": true,
          "ParameterType": "Data",
          "ParameterIndexes": [ 10, 11 ],
          "Factor": 1
        },
        {
          "Name": "(DSE) DI Status",
          "Signed": false,
          "EnableDataType": true,
          "MinVal": 0,
          "MaxVal": 0,
          "Field": "F2",
          "Expression": "{0} * 256 + {1}",
          "Precision": 5,
          "DataType": "Binary",
          "Evaluate": true,
          "ParameterType": "Data",
          "ParameterIndexes": [ 12, 13 ],
          "Factor": 1
        }
      ]
    },
    {
      "PageName": "Page154",
      "PageNumber": 154,
      "Parameters": [
        {
          "Name": "Device ID",
          "Signed": false,
          "EnableDataType": false,
          "MinVal": -1,
          "MaxVal": -1,
          "Field": "Id",
          "Expression": "{0}",
          "Precision": 0,
          "DataType": "String",
          "Evaluate": false,
          "ParameterType": "Id",
          "ParameterIndexes": [ 4 ],
          "Factor": 1
        },
        {
          "Name": "Timestamp",
          "Signed": false,
          "EnableDataType": false,
          "MinVal": -1,
          "MaxVal": -1,
          "Field": "DateAndTime",
          "Expression": "{0} * 256 * 256 * 256 + {1} * 256 * 256 + {2} * 256 + {3}",
          "Precision": 5,
          "DataType": "Epoch",
          "Evaluate": true,
          "ParameterType": "Data",
          "ParameterIndexes": [ 0, 1, 2, 3 ],
          "Factor": 1
        },
        {
          "Name": "DeviceId",
          "Signed": false,
          "EnableDataType": false,
          "MinVal": -1,
          "MaxVal": -1,
          "Field": "Id",
          "Expression": "{0}",
          "Precision": 0,
          "DataType": "Integer",
          "Evaluate": false,
          "ParameterType": "Data",
          "ParameterIndexes": [ 4 ],
          "Factor": 1
        },
        {
          "Name": "PageNumber",
          "Signed": false,
          "EnableDataType": false,
          "MinVal": -1,
          "MaxVal": -1,
          "Field": "Id",
          "Expression": "{0}",
          "Precision": 0,
          "DataType": "Integer",
          "Evaluate": false,
          "ParameterType": "Data",
          "ParameterIndexes": [ 6 ],
          "Factor": 1
        },
        {
          "Name": "(DSE) Number Of Named Alarms",
          "Signed": false,
          "EnableDataType": true,
          "MinVal": 0,
          "MaxVal": 0,
          "Field": "F1",
          "Expression": "{0} * 256 + {1}",
          "Precision": 5,
          "DataType": "Double",
          "Evaluate": true,
          "ParameterType": "Data",
          "ParameterIndexes": [ 10, 11 ],
          "Factor": 1
        },
        {
          "Name": "(DSE) Emergency Stop",
          "Signed": false,
          "EnableDataType": true,
          "MinVal": 0,
          "MaxVal": 0,
          "Field": "F2",
          "Expression": "{0} / 16 + 240",
          "Precision": 5,
          "DataType": "Integer",
          "Evaluate": true,
          "ParameterType": "Data",
          "ParameterIndexes": [ 12 ],
          "Factor": 1
        },
        {
          "Name": "(DSE) Low Oil Pressure",
          "Signed": false,
          "EnableDataType": true,
          "MinVal": 0,
          "MaxVal": 0,
          "Field": "F3",
          "Expression": "{0} / 1 + 15",
          "Precision": 5,
          "DataType": "Integer",
          "Evaluate": true,
          "ParameterType": "Data",
          "ParameterIndexes": [ 12 ],
          "Factor": 1
        },
        {
          "Name": "(DSE) High Coolant Temperature",
          "Signed": false,
          "EnableDataType": true,
          "MinVal": 0,
          "MaxVal": 0,
          "Field": "F4",
          "Expression": "{0} / 16 + 240",
          "Precision": 5,
          "DataType": "Integer",
          "Evaluate": true,
          "ParameterType": "Data",
          "ParameterIndexes": [ 13 ],
          "Factor": 1
        },
        {
          "Name": "(DSE) Low Coolant Temperature",
          "Signed": false,
          "EnableDataType": true,
          "MinVal": 0,
          "MaxVal": 0,
          "Field": "F5",
          "Expression": "{0} / 1 + 15",
          "Precision": 5,
          "DataType": "Integer",
          "Evaluate": true,
          "ParameterType": "Data",
          "ParameterIndexes": [ 13 ],
          "Factor": 1
        },
        {
          "Name": "(DSE) Under Speed",
          "Signed": false,
          "EnableDataType": true,
          "MinVal": 0,
          "MaxVal": 0,
          "Field": "F6",
          "Expression": "{0} / 16 + 240",
          "Precision": 5,
          "DataType": "Integer",
          "Evaluate": true,
          "ParameterType": "Data",
          "ParameterIndexes": [ 14 ],
          "Factor": 1
        },
        {
          "Name": "(DSE) Over Speed",
          "Signed": false,
          "EnableDataType": true,
          "MinVal": 0,
          "MaxVal": 0,
          "Field": "F7",
          "Expression": "{0} / 1 + 15",
          "Precision": 5,
          "DataType": "Integer",
          "Evaluate": true,
          "ParameterType": "Data",
          "ParameterIndexes": [ 14 ],
          "Factor": 1
        },
        {
          "Name": "(DSE) Generator Low Frequency",
          "Signed": false,
          "EnableDataType": true,
          "MinVal": 0,
          "MaxVal": 0,
          "Field": "F8",
          "Expression": "{0} / 16 + 240",
          "Precision": 5,
          "DataType": "Integer",
          "Evaluate": true,
          "ParameterType": "Data",
          "ParameterIndexes": [ 15 ],
          "Factor": 1
        },
        {
          "Name": "(DSE) Generator High Frequency",
          "Signed": false,
          "EnableDataType": true,
          "MinVal": 0,
          "MaxVal": 0,
          "Field": "F9",
          "Expression": "{0} / 1 + 15",
          "Precision": 5,
          "DataType": "Integer",
          "Evaluate": true,
          "ParameterType": "Data",
          "ParameterIndexes": [ 15 ],
          "Factor": 1
        },
        {
          "Name": "(DSE) Generator Low Voltage",
          "Signed": false,
          "EnableDataType": true,
          "MinVal": 0,
          "MaxVal": 0,
          "Field": "F10",
          "Expression": "{0} / 16 + 240",
          "Precision": 5,
          "DataType": "Integer",
          "Evaluate": true,
          "ParameterType": "Data",
          "ParameterIndexes": [ 16 ],
          "Factor": 1
        },
        {
          "Name": "(DSE) Generator High Voltage",
          "Signed": false,
          "EnableDataType": true,
          "MinVal": 0,
          "MaxVal": 0,
          "Field": "F11",
          "Expression": "{0} / 1 + 15",
          "Precision": 5,
          "DataType": "Integer",
          "Evaluate": true,
          "ParameterType": "Data",
          "ParameterIndexes": [ 16 ],
          "Factor": 1
        },
        {
          "Name": "(DSE) Low Battery Voltage",
          "Signed": false,
          "EnableDataType": true,
          "MinVal": 0,
          "MaxVal": 0,
          "Field": "F12",
          "Expression": "{0} / 16 + 240",
          "Precision": 5,
          "DataType": "Integer",
          "Evaluate": true,
          "ParameterType": "Data",
          "ParameterIndexes": [ 17 ],
          "Factor": 1
        },
        {
          "Name": "(DSE) High Battery Voltage",
          "Signed": false,
          "EnableDataType": true,
          "MinVal": 0,
          "MaxVal": 0,
          "Field": "F13",
          "Expression": "{0} / 1 + 15",
          "Precision": 5,
          "DataType": "Integer",
          "Evaluate": true,
          "ParameterType": "Data",
          "ParameterIndexes": [ 17 ],
          "Factor": 1
        },
        {
          "Name": "(DSE) Charge Alternator Failure",
          "Signed": false,
          "EnableDataType": true,
          "MinVal": 0,
          "MaxVal": 0,
          "Field": "F14",
          "Expression": "{0} / 16 + 240",
          "Precision": 5,
          "DataType": "Integer",
          "Evaluate": true,
          "ParameterType": "Data",
          "ParameterIndexes": [ 18 ],
          "Factor": 1
        },
        {
          "Name": "(DSE) Fail To Start",
          "Signed": false,
          "EnableDataType": true,
          "MinVal": 0,
          "MaxVal": 0,
          "Field": "F15",
          "Expression": "{0} / 1 + 15",
          "Precision": 5,
          "DataType": "Integer",
          "Evaluate": true,
          "ParameterType": "Data",
          "ParameterIndexes": [ 18 ],
          "Factor": 1
        },
        {
          "Name": "(DSE) Fail To Come To Rest",
          "Signed": false,
          "EnableDataType": true,
          "MinVal": 0,
          "MaxVal": 0,
          "Field": "F16",
          "Expression": "{0} / 16 + 240",
          "Precision": 5,
          "DataType": "Integer",
          "Evaluate": true,
          "ParameterType": "Data",
          "ParameterIndexes": [ 19 ],
          "Factor": 1
        },
        {
          "Name": "(DSE) Generator Failed To Close",
          "Signed": false,
          "EnableDataType": true,
          "MinVal": 0,
          "MaxVal": 0,
          "Field": "F17",
          "Expression": "{0} / 1 + 15",
          "Precision": 5,
          "DataType": "Integer",
          "Evaluate": true,
          "ParameterType": "Data",
          "ParameterIndexes": [ 19 ],
          "Factor": 1
        },
        {
          "Name": "(DSE) Mains Failed To Close",
          "Signed": false,
          "EnableDataType": true,
          "MinVal": 0,
          "MaxVal": 0,
          "Field": "F18",
          "Expression": "{0} / 16 + 240",
          "Precision": 5,
          "DataType": "Integer",
          "Evaluate": true,
          "ParameterType": "Data",
          "ParameterIndexes": [ 20 ],
          "Factor": 1
        },
        {
          "Name": "(DSE) Oil Pressure Sender Fault",
          "Signed": false,
          "EnableDataType": true,
          "MinVal": 0,
          "MaxVal": 0,
          "Field": "F19",
          "Expression": "{0} / 1 + 15",
          "Precision": 5,
          "DataType": "Integer",
          "Evaluate": true,
          "ParameterType": "Data",
          "ParameterIndexes": [ 20 ],
          "Factor": 1
        },
        {
          "Name": "(DSE) Magnetic Pickup Loss",
          "Signed": false,
          "EnableDataType": true,
          "MinVal": 0,
          "MaxVal": 0,
          "Field": "F20",
          "Expression": "{0} / 16 + 240",
          "Precision": 5,
          "DataType": "Integer",
          "Evaluate": true,
          "ParameterType": "Data",
          "ParameterIndexes": [ 21 ],
          "Factor": 1
        },
        {
          "Name": "(DSE) Magnetic Pickup Open Circuit",
          "Signed": false,
          "EnableDataType": true,
          "MinVal": 0,
          "MaxVal": 0,
          "Field": "F21",
          "Expression": "{0} / 1 + 15",
          "Precision": 5,
          "DataType": "Integer",
          "Evaluate": true,
          "ParameterType": "Data",
          "ParameterIndexes": [ 21 ],
          "Factor": 1
        },
        {
          "Name": "(DSE) Generator High Current",
          "Signed": false,
          "EnableDataType": true,
          "MinVal": 0,
          "MaxVal": 0,
          "Field": "F22",
          "Expression": "{0} / 16 + 240",
          "Precision": 5,
          "DataType": "Integer",
          "Evaluate": true,
          "ParameterType": "Data",
          "ParameterIndexes": [ 22 ],
          "Factor": 1
        },
        {
          "Name": "(DSE) Calibration Lost",
          "Signed": false,
          "EnableDataType": true,
          "MinVal": 0,
          "MaxVal": 0,
          "Field": "F23",
          "Expression": "{0} / 1 + 15",
          "Precision": 5,
          "DataType": "Integer",
          "Evaluate": true,
          "ParameterType": "Data",
          "ParameterIndexes": [ 22 ],
          "Factor": 1
        },
        {
          "Name": "(DSE) Low Fuel Level",
          "Signed": false,
          "EnableDataType": true,
          "MinVal": 0,
          "MaxVal": 0,
          "Field": "F24",
          "Expression": "{0} / 16 + 240",
          "Precision": 5,
          "DataType": "Integer",
          "Evaluate": true,
          "ParameterType": "Data",
          "ParameterIndexes": [ 23 ],
          "Factor": 1
        },
        {
          "Name": "(DSE) CAN ECU Warning",
          "Signed": false,
          "EnableDataType": true,
          "MinVal": 0,
          "MaxVal": 0,
          "Field": "F25",
          "Expression": "{0} / 1 + 15",
          "Precision": 5,
          "DataType": "Integer",
          "Evaluate": true,
          "ParameterType": "Data",
          "ParameterIndexes": [ 23 ],
          "Factor": 1
        },
        {
          "Name": "(DSE) CAN ECU Shutdown",
          "Signed": false,
          "EnableDataType": true,
          "MinVal": 0,
          "MaxVal": 0,
          "Field": "F26",
          "Expression": "{0} / 16 + 240",
          "Precision": 5,
          "DataType": "Integer",
          "Evaluate": true,
          "ParameterType": "Data",
          "ParameterIndexes": [ 24 ],
          "Factor": 1
        },
        {
          "Name": "(DSE) CAN ECU Data Fail",
          "Signed": false,
          "EnableDataType": true,
          "MinVal": 0,
          "MaxVal": 0,
          "Field": "F27",
          "Expression": "{0} / 1 + 15",
          "Precision": 5,
          "DataType": "Integer",
          "Evaluate": true,
          "ParameterType": "Data",
          "ParameterIndexes": [ 24 ],
          "Factor": 1
        },
        {
          "Name": "(DSE) Low Oil Level Switch",
          "Signed": false,
          "EnableDataType": true,
          "MinVal": 0,
          "MaxVal": 0,
          "Field": "F28",
          "Expression": "{0} / 16 + 240",
          "Precision": 5,
          "DataType": "Integer",
          "Evaluate": true,
          "ParameterType": "Data",
          "ParameterIndexes": [ 25 ],
          "Factor": 1
        },
        {
          "Name": "(DSE) High Temperature Switch",
          "Signed": false,
          "EnableDataType": true,
          "MinVal": 0,
          "MaxVal": 0,
          "Field": "F29",
          "Expression": "{0} / 1 + 15",
          "Precision": 5,
          "DataType": "Integer",
          "Evaluate": true,
          "ParameterType": "Data",
          "ParameterIndexes": [ 25 ],
          "Factor": 1
        },
        {
          "Name": "(DSE) Low Fuel Level Switch",
          "Signed": false,
          "EnableDataType": true,
          "MinVal": 0,
          "MaxVal": 0,
          "Field": "F30",
          "Expression": "{0} / 16 + 240",
          "Precision": 5,
          "DataType": "Integer",
          "Evaluate": true,
          "ParameterType": "Data",
          "ParameterIndexes": [ 26 ],
          "Factor": 1
        },
        {
          "Name": "(DSE) Expansion Unit Watchdog Alarm",
          "Signed": false,
          "EnableDataType": true,
          "MinVal": 0,
          "MaxVal": 0,
          "Field": "F31",
          "Expression": "{0} / 1 + 15",
          "Precision": 5,
          "DataType": "Integer",
          "Evaluate": true,
          "ParameterType": "Data",
          "ParameterIndexes": [ 26 ],
          "Factor": 1
        },
        {
          "Name": "Reserved",
          "Signed": false,
          "EnableDataType": true,
          "MinVal": 0,
          "MaxVal": 0,
          "Field": "F32",
          "Expression": "{0} / 16 + 240",
          "Precision": 5,
          "DataType": "Integer",
          "Evaluate": true,
          "ParameterType": "Data",
          "ParameterIndexes": [ 27 ],
          "Factor": 1
        },
        {
          "Name": "Reserved",
          "Signed": false,
          "EnableDataType": true,
          "MinVal": 0,
          "MaxVal": 0,
          "Field": "F33",
          "Expression": "{0} / 1 + 15",
          "Precision": 5,
          "DataType": "Integer",
          "Evaluate": true,
          "ParameterType": "Data",
          "ParameterIndexes": [ 27 ],
          "Factor": 1
        }

      ]
    },
    {
      "PageName": "Page190",
      "PageNumber": 190,
      "Parameters": [
        {
          "Name": "Device ID",
          "Signed": false,
          "EnableDataType": false,
          "MinVal": -1,
          "MaxVal": -1,
          "Field": "Id",
          "Expression": "{0}",
          "Precision": 0,
          "DataType": "String",
          "Evaluate": false,
          "ParameterType": "Id",
          "ParameterIndexes": [ 4 ],
          "Factor": 1
        },
        {
          "Name": "Timestamp",
          "Signed": false,
          "EnableDataType": false,
          "MinVal": -1,
          "MaxVal": -1,
          "Field": "DateAndTime",
          "Expression": "{0} * 256 * 256 * 256 + {1} * 256 * 256 + {2} * 256 + {3}",
          "Precision": 5,
          "DataType": "Epoch",
          "Evaluate": true,
          "ParameterType": "Data",
          "ParameterIndexes": [ 0, 1, 2, 3 ],
          "Factor": 1
        },
        {
          "Name": "DeviceId",
          "Signed": false,
          "EnableDataType": false,
          "MinVal": -1,
          "MaxVal": -1,
          "Field": "Id",
          "Expression": "{0}",
          "Precision": 0,
          "DataType": "Integer",
          "Evaluate": false,
          "ParameterType": "Data",
          "ParameterIndexes": [ 4 ],
          "Factor": 1
        },
        {
          "Name": "PageNumber",
          "Signed": false,
          "EnableDataType": false,
          "MinVal": -1,
          "MaxVal": -1,
          "Field": "Id",
          "Expression": "{0}",
          "Precision": 0,
          "DataType": "Integer",
          "Evaluate": false,
          "ParameterType": "Data",
          "ParameterIndexes": [ 6 ],
          "Factor": 1
        },
        {
          "Name": "(DSE) Fuel Solenoid Relay",
          "Signed": false,
          "EnableDataType": true,
          "MinVal": 0,
          "MaxVal": 0,
          "Field": "F1",
          "Expression": "{0} * 256 + {1}",
          "Precision": 5,
          "DataType": "Integer",
          "Evaluate": true,
          "ParameterType": "Data",
          "ParameterIndexes": [ 10, 11 ],
          "Factor": 1
        },
        {
          "Name": "(DSE) Crank Relay",
          "Signed": false,
          "EnableDataType": true,
          "MinVal": 0,
          "MaxVal": 0,
          "Field": "F2",
          "Expression": "{0} * 256 + {1}",
          "Precision": 5,
          "DataType": "Integer",
          "Evaluate": true,
          "ParameterType": "Data",
          "ParameterIndexes": [ 12, 13 ],
          "Factor": 1
        },
        {
          "Name": "(DSE) Digital Output E",
          "Signed": false,
          "EnableDataType": true,
          "MinVal": 0,
          "MaxVal": 0,
          "Field": "F3",
          "Expression": "{0} * 256 + {1}",
          "Precision": 5,
          "DataType": "Integer",
          "Evaluate": true,
          "ParameterType": "Data",
          "ParameterIndexes": [ 14, 15 ],
          "Factor": 1
        },
        {
          "Name": "(DSE) Digital Output F",
          "Signed": false,
          "EnableDataType": true,
          "MinVal": 0,
          "MaxVal": 0,
          "Field": "F4",
          "Expression": "{0} * 256 + {1}",
          "Precision": 5,
          "DataType": "Integer",
          "Evaluate": true,
          "ParameterType": "Data",
          "ParameterIndexes": [ 16, 17 ],
          "Factor": 1
        },
        {
          "Name": "(DSE) Digital Output G",
          "Signed": false,
          "EnableDataType": true,
          "MinVal": 0,
          "MaxVal": 0,
          "Field": "F5",
          "Expression": "{0} * 256 + {1}",
          "Precision": 5,
          "DataType": "Integer",
          "Evaluate": true,
          "ParameterType": "Data",
          "ParameterIndexes": [ 18, 19 ],
          "Factor": 1
        },
        {
          "Name": "(DSE) Digital Output H",
          "Signed": false,
          "EnableDataType": true,
          "MinVal": 0,
          "MaxVal": 0,
          "Field": "F6",
          "Expression": "{0} * 256 + {1}",
          "Precision": 5,
          "DataType": "Integer",
          "Evaluate": true,
          "ParameterType": "Data",
          "ParameterIndexes": [ 20, 21 ],
          "Factor": 1
        },
        {
          "Name": "(DSE) Genset On Load  ",
          "Signed": false,
          "EnableDataType": true,
          "MinVal": 0,
          "MaxVal": 0,
          "Field": "F7",
          "Expression": "{0} * 256 + {1}",
          "Precision": 5,
          "DataType": "Integer",
          "Evaluate": true,
          "ParameterType": "Data",
          "ParameterIndexes": [ 22, 23 ],
          "Factor": 1
        },
        {
          "Name": "(DSE) Mains On Load  ",
          "Signed": false,
          "EnableDataType": true,
          "MinVal": 0,
          "MaxVal": 0,
          "Field": "F8",
          "Expression": "{0} * 256 + {1}",
          "Precision": 5,
          "DataType": "Integer",
          "Evaluate": true,
          "ParameterType": "Data",
          "ParameterIndexes": [ 24, 25 ],
          "Factor": 1
        },
        {
          "Name": "(DSE) Stop LED",
          "Signed": false,
          "EnableDataType": true,
          "MinVal": 0,
          "MaxVal": 0,
          "Field": "F9",
          "Expression": "{0} * 256 + {1}",
          "Precision": 5,
          "DataType": "Integer",
          "Evaluate": true,
          "ParameterType": "Data",
          "ParameterIndexes": [ 26, 27 ],
          "Factor": 1
        },
        {
          "Name": "(DSE) Manual LED",
          "Signed": false,
          "EnableDataType": true,
          "MinVal": 0,
          "MaxVal": 0,
          "Field": "F10",
          "Expression": "{0} * 256 + {1}",
          "Precision": 5,
          "DataType": "Integer",
          "Evaluate": true,
          "ParameterType": "Data",
          "ParameterIndexes": [ 28, 29 ],
          "Factor": 1
        },
        {
          "Name": "(DSE) TEST LED",
          "Signed": false,
          "EnableDataType": true,
          "MinVal": 0,
          "MaxVal": 0,
          "Field": "F11",
          "Expression": "{0} * 256 + {1}",
          "Precision": 5,
          "DataType": "Integer",
          "Evaluate": true,
          "ParameterType": "Data",
          "ParameterIndexes": [ 30, 31 ],
          "Factor": 1
        },
        {
          "Name": "(DSE) AUTO LED",
          "Signed": false,
          "EnableDataType": true,
          "MinVal": 0,
          "MaxVal": 0,
          "Field": "F12",
          "Expression": "{0} * 256 + {1}",
          "Precision": 5,
          "DataType": "Integer",
          "Evaluate": true,
          "ParameterType": "Data",
          "ParameterIndexes": [ 32, 33 ],
          "Factor": 1
        },
        {
          "Name": "(DSE) Mains Available",
          "Signed": false,
          "EnableDataType": true,
          "MinVal": 0,
          "MaxVal": 0,
          "Field": "F13",
          "Expression": "{0} * 256 + {1}",
          "Precision": 5,
          "DataType": "Integer",
          "Evaluate": true,
          "ParameterType": "Data",
          "ParameterIndexes": [ 34, 35 ],
          "Factor": 1
        },
        {
          "Name": "(DSE) Mains Breaker LED",
          "Signed": false,
          "EnableDataType": true,
          "MinVal": 0,
          "MaxVal": 0,
          "Field": "F14",
          "Expression": "{0} * 256 + {1}",
          "Precision": 5,
          "DataType": "Integer",
          "Evaluate": true,
          "ParameterType": "Data",
          "ParameterIndexes": [ 36, 37 ],
          "Factor": 1
        },
        {
          "Name": "(DSE) Genset Breaker LED",
          "Signed": false,
          "EnableDataType": true,
          "MinVal": 0,
          "MaxVal": 0,
          "Field": "F15",
          "Expression": "{0} * 256 + {1}",
          "Precision": 5,
          "DataType": "Integer",
          "Evaluate": true,
          "ParameterType": "Data",
          "ParameterIndexes": [ 38, 39 ],
          "Factor": 1
        },
        {
          "Name": "(DSE) Genset Available",
          "Signed": false,
          "EnableDataType": true,
          "MinVal": 0,
          "MaxVal": 0,
          "Field": "F16",
          "Expression": "{0} * 256 + {1}",
          "Precision": 5,
          "DataType": "Integer",
          "Evaluate": true,
          "ParameterType": "Data",
          "ParameterIndexes": [ 40, 41 ],
          "Factor": 1
        }

      ]
    }

  ]

}